Metadata-Version: 2.1
Name: netunicorn-connector-kubernetes
Version: 0.0.2
Summary: Kubernetes connector for netunicorn
Author-email: Roman Beltiukov <rbeltiukov@ucsb.edu>
License: MIT
Keywords: netunicorn
Classifier: Programming Language :: Python :: 3
Requires-Python: >=3.10
License-File: LICENSE
Requires-Dist: netunicorn-base (>=0.3.1)
Requires-Dist: kubernetes
Requires-Dist: pyyaml
